openadbapi/API.py
openadbapi/__init__.py
openadbapi/_version.py
openadbapi-0.0.1.dist-info/METADATA
openadbapi-0.0.1.dist-info/WHEEL
openadbapi-0.0.1.dist-info/top_level.txt
openadbapi-0.0.1.dist-info/RECORD
