Metadata-Version: 2.4
Name: openadbapi
Version: 0.0.1
Summary: OpenADB-API
Home-page: https://gitlab.lrz.de/openadb/python3-openadbapi
Author: Christian Schwatke
Author-email: christian.schwatke@tum.de
License: MIT
Dynamic: author
Dynamic: author-email
Dynamic: description
Dynamic: description-content-type
Dynamic: home-page
Dynamic: license
Dynamic: summary
